{
  "generatedAt": "2026-06-15T04:43:51.671Z",
  "newCount": 4,
  "items": [
    {
      "id": "sdc-e:sdc-e:1935231",
      "schoolId": "sdc-e",
      "schoolName": "도촌초등학교",
      "schoolHomepage": "https://sdc-e.goesn.kr",
      "boardLabel": "공지사항",
      "boardUrl": "https://sdc-e.goesn.kr/sdc-e/na/ntt/selectNttList.do?mi=17317&bbsId=14031&listCo=50&currPage=1",
      "postedAt": "2026-06-14T15:00:00.000Z",
      "deadline": null,
      "title": "2026 청소년 힐링데이(캠프) 참가자 모집",
      "url": "https://sdc-e.goesn.kr/sdc-e/na/ntt/selectNttInfo.do?mi=17317&bbsId=14031&nttSn=1935231"
    },
    {
      "id": "office:goesn:1935421",
      "schoolId": null,
      "schoolName": "성남교육지원청 구인",
      "schoolHomepage": "https://www.goesn.kr",
      "boardLabel": "성남교육지원청 구인",
      "boardUrl": "https://www.goesn.kr/goesn/na/ntt/selectNttList.do?bbsId=17872&mi=23603&listCo=50&currPage=1",
      "postedAt": "2026-06-14T15:00:00.000Z",
      "deadline": "2026-06-21T15:00:00.000Z",
      "title": "2026년 초1~2맞춤형 아이신나 플러스 여름방학 프로그램 개인 위탁 강사 공고(요리4일, 풍선아트 2일)",
      "url": "https://www.goesn.kr/goesn/na/ntt/selectNttInfo.do?bbsId=17872&mi=23603&nttSn=1935421"
    },
    {
      "id": "office:goesn:1935217",
      "schoolId": null,
      "schoolName": "성남교육지원청 구인",
      "schoolHomepage": "https://www.goesn.kr",
      "boardLabel": "성남교육지원청 구인",
      "boardUrl": "https://www.goesn.kr/goesn/na/ntt/selectNttList.do?bbsId=17872&mi=23603&listCo=50&currPage=1",
      "postedAt": "2026-06-14T15:00:00.000Z",
      "deadline": "2026-06-21T15:00:00.000Z",
      "title": "2026 분당초 여름방학 아이신나플러스 개인위탁 강사 채용 공고(놀이체육)",
      "url": "https://www.goesn.kr/goesn/na/ntt/selectNttInfo.do?bbsId=17872&mi=23603&nttSn=1935217"
    },
    {
      "id": "office:goesn:1935216",
      "schoolId": null,
      "schoolName": "성남교육지원청 구인",
      "schoolHomepage": "https://www.goesn.kr",
      "boardLabel": "성남교육지원청 구인",
      "boardUrl": "https://www.goesn.kr/goesn/na/ntt/selectNttList.do?bbsId=17872&mi=23603&listCo=50&currPage=1",
      "postedAt": "2026-06-14T15:00:00.000Z",
      "deadline": "2026-06-21T15:00:00.000Z",
      "title": "2026 분당초 여름방학 아이신나플러스 보조 강사 채용 공고",
      "url": "https://www.goesn.kr/goesn/na/ntt/selectNttInfo.do?bbsId=17872&mi=23603&nttSn=1935216"
    }
  ]
}
