{
  "generatedAt": "2026-06-16T10:50:38.616Z",
  "hitCount": 3,
  "errors": [],
  "items": [
    {
      "id": "seoul:dgedu:10081",
      "schoolId": null,
      "schoolName": "(대림초)한국어 강사 채용 공고",
      "schoolHomepage": null,
      "boardLabel": "서울 동작관악 구인",
      "boardUrl": "https://dgedu.sen.go.kr/FUS/JO/JOL11.do",
      "postedAt": null,
      "deadline": "2026-06-16T00:00:00+09:00",
      "title": "강사 (2026-06-12)",
      "url": "https://dgedu.sen.go.kr/FUS/JO/JOL11.do"
    },
    {
      "id": "seoul:sbedu:5545",
      "schoolId": "sen-7031278",
      "schoolName": "서울가재울초등학교",
      "schoolHomepage": null,
      "boardLabel": "서울 서부(은평·서대문·마포) 구인",
      "boardUrl": "https://sbedu.sen.go.kr/FUS/JO/JOL11.do",
      "postedAt": null,
      "deadline": "2026-06-17T00:00:00+09:00",
      "title": "맞춤형교실 개인위탁 외부강사",
      "url": "https://sbedu.sen.go.kr/FUS/JO/JOL11.do"
    },
    {
      "id": "seoul:sbedu:5546",
      "schoolId": "sen-7031141",
      "schoolName": "서울신도초등학교",
      "schoolHomepage": null,
      "boardLabel": "서울 서부(은평·서대문·마포) 구인",
      "boardUrl": "https://sbedu.sen.go.kr/FUS/JO/JOL11.do",
      "postedAt": null,
      "deadline": "2026-06-18T00:00:00+09:00",
      "title": "문화예술협력강사 (시간제)",
      "url": "https://sbedu.sen.go.kr/FUS/JO/JOL11.do"
    }
  ]
}
